netrun/__init__.py
netrun/graph.py
netrun-0.1.0.dist-info/METADATA
netrun-0.1.0.dist-info/WHEEL
netrun-0.1.0.dist-info/top_level.txt
netrun-0.1.0.dist-info/RECORD
