Metadata-Version: 2.4
Name: netrun
Version: 0.1.0
Summary: A flow-based development (FBD) runtime system.
Requires-Python: >=3.11
Requires-Dist: netrun-sim>=0.1.1
